 [
        {
            "id": 1,
            "type": "small",
            "name": "Heineken",
            "imgPath": "https://www.heineken.com/media-us/01pfxdqq/heineken-original-bottle.png?quality=85",
            "price": 4.55
        },
        {
            "id": 2,
            "type": "medium",
            "name": "Heineken",
            "imgPath": "https://www.heineken.com/media-us/01pfxdqq/heineken-original-bottle.png?quality=85",
            "price": 5.55
        },
        {
            "id": 3,
            "type": "small",
            "name": "Ceres",
            "imgPath": "https://www.wine-searcher.com/images/labels/23/16/10622316.jpg",
            "price": 3.55
        },
        {
            "id": 4,
            "type": "medium",
            "name": "Ceres",
            "imgPath": "https://www.wine-searcher.com/images/labels/23/16/10622316.jpg",
            "price": 4.34
        },
        {
            "id": 5,
            "type": "small",
            "name": "Carlsberg",
            "imgPath": "https://www.bigbasket.com/media/uploads/p/xxl/40198496_3-carlsberg-elephant-premium-strong-beer.jpg",
            "price": 4.10
        },
        {
            "id": 6,
            "type": "medium",
            "name": "Carlsberg",
            "imgPath": "https://www.bigbasket.com/media/uploads/p/xxl/40198496_3-carlsberg-elephant-premium-strong-beer.jpg",
            "price": 5.10
        },
        {
            "id": 7,
            "type": "small",
            "name": "Tuborg",
            "imgPath": "https://www.bigbasket.com/media/uploads/p/xxl/40198501_3-tuborg-strong-1880-beer.jpg",
            "price": 4.35
        },
        {
            "id": 8,
            "type": "medium",
            "name": "Tuborg",
            "imgPath": "https://www.bigbasket.com/media/uploads/p/xxl/40198501_3-tuborg-strong-1880-beer.jpg",
            "price": 5.55
        },
        {
            "id": 9,
            "type": "small",
            "name": "Corona",
            "imgPath": "https://upload.wikimedia.org/wikipedia/commons/0/04/Corona_Extra_beer_bottle_%282019%29.png",
            "price": 5.15
        },
        {
            "id": 10,
            "type": "medium",
            "name": "Corona",
            "imgPath": "https://upload.wikimedia.org/wikipedia/commons/0/04/Corona_Extra_beer_bottle_%282019%29.png",
            "price": 5.65
        }

    ]